gestures.py
pythonista_gestures-1.2.1.dist-info/WHEEL
pythonista_gestures-1.2.1.dist-info/METADATA
pythonista_gestures-1.2.1.dist-info/RECORD
