Metadata-Version: 2.1
Name: pythonista-gestures
Version: 1.2.1
Summary: Gestures wrapper for iOS
Home-page: https://github.com/mikaelho/pythonista-gestures
License: The Unlicense
Author: Mikael Honkala
Author-email: mikael.honkala@gmail.com
Classifier: Operating System :: iOS
